vm_balancer/__init__.py
vm_balancer/__main__.py
vm_balancer/main.py
vm_balancer/api/__init__.py
vm_balancer/api/client.py
vm_balancer/core/__init__.py
vm_balancer/core/balancer.py
vm_balancer/models/__init__.py
vm_balancer/models/cluster.py
vm_balancer/models/node.py
vm_balancer/models/vm.py
vm_balancer/monitoring/__init__.py
vm_balancer/monitoring/ssh.py
vm_balancer/notifications/__init__.py
vm_balancer/notifications/telegram.py
vm_balancer/utils/__init__.py
vm_balancer/utils/env.py
vm_balancer/utils/i18n.py
vm_balancer-2.0.1.dist-info/licenses/LICENSE
vm_balancer-2.0.1.dist-info/METADATA
vm_balancer-2.0.1.dist-info/WHEEL
vm_balancer-2.0.1.dist-info/entry_points.txt
vm_balancer-2.0.1.dist-info/top_level.txt
vm_balancer-2.0.1.dist-info/RECORD
