Metadata-Version: 2.4
Name: vm-balancer
Version: 2.0.1
Summary: Intelligent auto-balancer for VMManager 6 virtual machines
Home-page: https://github.com/DenisKoleda/vm-balancer
Author: Denis Koleda
Author-email: VMBalancer Team <support@vmbalancer.com>
License-Expression: MIT
Project-URL: Homepage, https://github.com/vmbalancer/vm-balancer
Project-URL: Documentation, https://vm-balancer.readthedocs.io/
Project-URL: Repository, https://github.com/vmbalancer/vm-balancer.git
Project-URL: Bug Tracker, https://github.com/vmbalancer/vm-balancer/issues
Keywords: vmware,virtualization,load-balancing,cluster,automation
Classifier: Development Status :: 5 - Production/Stable
Classifier: Intended Audience :: System Administrators
Classifier: Operating System :: OS Independent
Classifier: Programming Language :: Python :: 3
Classifier: Programming Language :: Python :: 3.8
Classifier: Programming Language :: Python :: 3.9
Classifier: Programming Language :: Python :: 3.10
Classifier: Programming Language :: Python :: 3.11
Classifier: Topic :: System :: Systems Administration
Classifier: Topic :: System :: Clustering
Requires-Python: >=3.8
License-File: LICENSE
Requires-Dist: requests>=2.28.0
Requires-Dist: python-dotenv>=0.19.0
Requires-Dist: urllib3>=1.26.0
Requires-Dist: rich>=13.0.0
Requires-Dist: colorama>=0.4.0
Requires-Dist: asyncssh>=2.21.0
Provides-Extra: dev
Requires-Dist: pytest>=7.0.0; extra == "dev"
Requires-Dist: pytest-asyncio>=0.21.0; extra == "dev"
Requires-Dist: black>=22.0.0; extra == "dev"
Requires-Dist: flake8>=5.0.0; extra == "dev"
Requires-Dist: mypy>=1.0.0; extra == "dev"
Requires-Dist: isort>=5.10.0; extra == "dev"
Provides-Extra: test
Requires-Dist: pytest>=7.0.0; extra == "test"
Requires-Dist: pytest-asyncio>=0.21.0; extra == "test"
Requires-Dist: pytest-cov>=4.0.0; extra == "test"
Dynamic: author
Dynamic: home-page
Dynamic: license-file
Dynamic: requires-python
